g2x_helpers/__init__.py
g2x_helpers/utils.py
g2x_helpers/pyfpds/__init__.py
g2x_helpers/pysam/__init__.py
g2x_helpers/pysam/sam.py
g2x_helpers-0.5.46.dist-info/DESCRIPTION.rst
g2x_helpers-0.5.46.dist-info/METADATA
g2x_helpers-0.5.46.dist-info/RECORD
g2x_helpers-0.5.46.dist-info/WHEEL
g2x_helpers-0.5.46.dist-info/metadata.json
g2x_helpers-0.5.46.dist-info/top_level.txt
